Metadata-Version: 1.0
Name: e2e
Version: 0.1.0
Summary: e2e
Home-page: UNKNOWN
Author: sbneto
Author-email: UNKNOWN
License: UNKNOWN
Platform: UNKNOWN
